{"ticker":"SPXJ.MI","history":[{"date":"2026-05-13","ts":"2026-05-13 01:11 CET","signal":"WATCH","price":47.93,"score":57.8,"er":0.2742},{"date":"2026-05-15","ts":"2026-05-15 17:55 CET","signal":"SELL","price":47.555,"score":14.8,"er":0.0116},{"date":"2026-05-22","ts":"2026-05-22 12:55 CET","signal":"WATCH","price":65.07,"score":47.1,"er":0.2795},{"date":"2026-05-22","ts":"2026-05-22 14:12 CET","signal":"SELL","price":47.63,"score":32.1,"er":0.0604},{"date":"2026-06-02","ts":"2026-06-02 19:59 CET","signal":"BUY1","price":48.22,"score":52.0,"er":0.4486},{"date":"2026-06-03","ts":"2026-06-03 14:46 CET","signal":"WATCH","price":48.195,"score":49.1,"er":0.3159},{"date":"2026-06-05","ts":"2026-06-05 13:32 CET","signal":"SELL","price":46.895,"score":23.3,"er":0.2113},{"date":"2026-06-15","ts":"2026-06-15 16:28 CET","signal":"WATCH","price":47.68,"score":23.9,"er":0.0203},{"date":"2026-06-19","ts":"2026-06-19 15:27 CET","signal":"BUY1","price":47.68,"score":62.5,"er":0.4003},{"date":"2026-06-19","ts":"2026-06-19 18:27 CET","signal":"WATCH","price":47.675,"score":62.4,"er":0.398},{"date":"2026-06-26","ts":"2026-06-26 14:06 CET","signal":"SELL","price":47.195,"score":27.6,"er":0.1987},{"date":"2026-06-26","ts":"2026-06-26 20:10 CET","signal":"WATCH","price":47.47,"score":30.2,"er":0.321},{"date":"2026-06-30","ts":"2026-06-30 14:03 CET","signal":"SELL","price":47.375,"score":33.7,"er":0.3377},{"date":"2026-07-06","ts":"2026-07-06 14:08 CET","signal":"WATCH","price":47.895,"score":34.0,"er":0.0211},{"date":"2026-07-14","ts":"2026-07-14 12:02 CET","signal":"BUY2","price":48.635,"score":67.9,"er":0.599},{"date":"2026-07-16","ts":"2026-07-16 12:14 CET","signal":"WATCH","price":48.605,"score":55.5,"er":0.351},{"date":"2026-07-17","ts":"2026-07-17 17:04 CET","signal":"BUY2","price":48.75,"score":66.0,"er":0.6174},{"date":"2026-07-20","ts":"2026-07-20 17:43 CET","signal":"WATCH","price":48.63,"score":65.7,"er":0.4641},{"date":"2026-07-21","ts":"2026-07-21 12:28 CET","signal":"BUY2","price":48.78,"score":68.8,"er":0.5861},{"date":"2026-07-22","ts":"2026-07-22 13:41 CET","signal":"WATCH","price":49.18,"score":49.4,"er":0.7306}]}